fastapi_radar/__init__.py
fastapi_radar/api.py
fastapi_radar/background.py
fastapi_radar/capture.py
fastapi_radar/middleware.py
fastapi_radar/models.py
fastapi_radar/radar.py
fastapi_radar/tracing.py
fastapi_radar/utils.py
fastapi_radar/dashboard/dist/index.html
fastapi_radar/dashboard/dist/assets/index-BQIU9U77.js
fastapi_radar/dashboard/dist/assets/index-D51YrvFG.css
fastapi_radar/dashboard/node_modules/flatted/python/flatted.py
fastapi_radar-0.3.2.dist-info/licenses/LICENSE
fastapi_radar-0.3.2.dist-info/METADATA
fastapi_radar-0.3.2.dist-info/WHEEL
fastapi_radar-0.3.2.dist-info/top_level.txt
fastapi_radar-0.3.2.dist-info/RECORD
