Metadata-Version: 2.4
Name: fastapi-radar
Version: 0.3.2
Summary: A debugging dashboard for FastAPI applications with real-time monitoring
Home-page: https://github.com/doganarif/fastapi-radar
Author: Arif Dogan
Author-email: Arif Dogan <me@arif.sh>
License: MIT
Project-URL: Homepage, https://github.com/doganarif/fastapi-radar
Project-URL: Bug Reports, https://github.com/doganarif/fastapi-radar/issues
Project-URL: Source, https://github.com/doganarif/fastapi-radar
Keywords: fastapi,debugging,monitoring,dashboard,development-tools
Classifier: Development Status :: 4 - Beta
Classifier: Intended Audience :: Developers
Classifier: Programming Language :: Python :: 3
Classifier: Programming Language :: Python :: 3.9
Classifier: Programming Language :: Python :: 3.10
Classifier: Programming Language :: Python :: 3.11
Classifier: Programming Language :: Python :: 3.12
Classifier: Framework :: FastAPI
Classifier: Topic :: Software Development :: Debuggers
Classifier: Topic :: Software Development :: Libraries :: Python Modules
Requires-Python: >=3.8
License-File: LICENSE
Requires-Dist: fastapi
Requires-Dist: sqlalchemy>=2.0
Requires-Dist: pydantic
Requires-Dist: starlette
Requires-Dist: duckdb==1.1.3
Requires-Dist: duckdb-engine==0.17.0
Requires-Dist: aiosqlite>=0.21.0
Provides-Extra: dev
Requires-Dist: pytest; extra == "dev"
Requires-Dist: pytest-asyncio; extra == "dev"
Requires-Dist: uvicorn[standard]; extra == "dev"
Requires-Dist: black; extra == "dev"
Requires-Dist: isort; extra == "dev"
Requires-Dist: flake8; extra == "dev"
Requires-Dist: mypy; extra == "dev"
Requires-Dist: httpx; extra == "dev"
Provides-Extra: release
Requires-Dist: build; extra == "release"
Requires-Dist: twine; extra == "release"
Dynamic: author
Dynamic: home-page
Dynamic: license-file
Dynamic: requires-python
